[
  {
    "uuid": "2380cb4c-4578-42fa-8b74-1bf932cd758b",
    "id": 0,
    "iteration": 0,
    "description": "Foo task 1",
    "project": "Foo",
    "status": "ready",
    "createdAt": 1742654369774,
    "completedAt": null,
    "repeatInterval": 86400000
  },
  {
    "uuid": "16e9a764-ae1e-4fa9-ae8d-ec81195a2938",
    "id": 1,
    "iteration": 0,
    "description": "Bar task 1",
    "project": "Bar",
    "status": "ready",
    "createdAt": 1742654385883,
    "completedAt": null,
    "repeatInterval": 86400000
  }
]